pymt_era5/__init__.py
pymt_era5/bmi.py
pymt_era5/data/.DS_Store
pymt_era5/data/Era5/api.yaml
pymt_era5/data/Era5/config_file.yaml
pymt_era5/data/Era5/info.yaml
pymt_era5/data/Era5/parameters.yaml
pymt_era5/data/Era5/run.yaml
pymt_era5-0.1.dist-info/LICENSE
pymt_era5-0.1.dist-info/METADATA
pymt_era5-0.1.dist-info/WHEEL
pymt_era5-0.1.dist-info/entry_points.txt
pymt_era5-0.1.dist-info/top_level.txt
pymt_era5-0.1.dist-info/RECORD
